tests/__init__.py
tests/test_validate_utf8.py
validate_utf8/__init__.py
validate_utf8/cli.py
validate_utf8/find_utf8_errors.py
validate_utf8-0.1.dist-info/LICENSE
validate_utf8-0.1.dist-info/METADATA
validate_utf8-0.1.dist-info/WHEEL
validate_utf8-0.1.dist-info/entry_points.txt
validate_utf8-0.1.dist-info/top_level.txt
validate_utf8-0.1.dist-info/RECORD
