Metadata-Version: 2.1
Name: validate-utf8
Version: 0.1
Summary: Python library and CLI for validating UTF-8 text
Home-page: https://github.com/simonw/validate-utf8
Author: Simon Willison
License: Apache License, Version 2.0
Platform: UNKNOWN
Classifier: Development Status :: 3 - Alpha
Classifier: Intended Audience :: Developers
Classifier: Intended Audience :: Science/Research
Classifier: Intended Audience :: End Users/Desktop
Classifier: License :: OSI Approved :: Apache Software License
Classifier: Programming Language :: Python :: 3.6
Classifier: Programming Language :: Python :: 3.7
Requires-Dist: click
Provides-Extra: test
Requires-Dist: pytest ; extra == 'test'
